simplemaml.py
simplemaml-1.2.13.dist-info/LICENSE
simplemaml-1.2.13.dist-info/METADATA
simplemaml-1.2.13.dist-info/WHEEL
simplemaml-1.2.13.dist-info/top_level.txt
simplemaml-1.2.13.dist-info/RECORD
