Metadata-Version: 2.1
Name: simplemaml
Version: 1.2.13
Summary: A generic Python and TensorFlow function that implements a simple version of the "Model-Agnostic Meta-Learning (MAML) Algorithm for Fast Adaptation of Deep Networks" as designed by Chelsea Finn et al. 2017
Home-page: https://github.com/AnasNeumann/simplemaml
Author: Anas Neumann
Author-email: anas.neumann.1@ulaval.ca
Classifier: Programming Language :: Python :: 3
Classifier: License :: OSI Approved :: MIT License
Classifier: Operating System :: OS Independent
Requires-Python: >=3.11
License-File: LICENSE
Requires-Dist: numpy
Requires-Dist: tensorflow
